runce/__init__.py
runce/__main__.py
runce/cli.py
runce/main.py
runce/procdb.py
runce/spawn.py
runce/utils.py
runce-0.4.3.dist-info/licenses/LICENSE
runce-0.4.3.dist-info/METADATA
runce-0.4.3.dist-info/WHEEL
runce-0.4.3.dist-info/entry_points.txt
runce-0.4.3.dist-info/top_level.txt
runce-0.4.3.dist-info/RECORD
