Metadata-Version: 2.4
Name: runce
Version: 0.4.3
Summary: Ensure only one instance of your process runs at a time.
Author: Jet-Logic
Project-URL: Homepage, https://github.com/jet-logic/runce
Project-URL: Documentation, https://github.com/jet-logic/runce#readme
Project-URL: Repository, https://github.com/jet-logic/runce
Classifier: Operating System :: POSIX :: Linux
Classifier: Development Status :: 4 - Beta
Classifier: Intended Audience :: Developers
Classifier: Programming Language :: Python :: 3
Requires-Python: >=3.8
License-File: LICENSE
Dynamic: license-file
